.coveragerc
.gitignore
CONTRIBUTING.md
LICENSE.txt
Pipfile
Pipfile.lock
README.md
setup.py
.github/workflows/test.yml
md2notion/NotionPyRenderer.py
md2notion/__init__.py
md2notion/__main__.py
md2notion/upload.py
md2notion_aaron_fork.egg-info/PKG-INFO
md2notion_aaron_fork.egg-info/SOURCES.txt
md2notion_aaron_fork.egg-info/dependency_links.txt
md2notion_aaron_fork.egg-info/requires.txt
md2notion_aaron_fork.egg-info/top_level.txt
tests/COMPREHENSIVE_TEST.md
tests/TEST IMAGE HAS SPACES.png
tests/TEST.md
tests/TEST_IMAGE.png
tests/__init__.py
tests/conftest.py
tests/test_NotionPyRenderer.py
tests/test_upload.py