Metadata-Version: 2.1
Name: md2notion-aaron-fork
Version: 2.4.1
Summary: Utilities for importing Markdown files to Notion.so
Home-page: https://github.com/Cobertos/md2notion/
Author: Cobertos
Author-email: me+python@cobertos.com
License: MIT
Keywords: notion notion.so notion-py markdown md converter
Classifier: Development Status :: 5 - Production/Stable
Classifier: Intended Audience :: Developers
Classifier: License :: OSI Approved :: MIT License
Classifier: Programming Language :: Python :: 3.6
Classifier: Programming Language :: Python :: 3.7
Classifier: Programming Language :: Python :: 3.8
Classifier: Topic :: Office/Business :: News/Diary
Classifier: Topic :: System :: Filesystems
Classifier: Topic :: Text Processing :: Markup :: Markdown
Classifier: Topic :: Utilities
License-File: LICENSE.txt
